Final/Final.srcs/sources_1/imports/new/full_adder.v
`timescale 1ns / 1ps
//////////////////////////////////////////////////////////////////////////////////
// Company: 
// Engineer: 
// 
// Create Date: 02/21/2023 02:21:50 PM
// Design Name: 
// Module Name: full_adder
// Project Name: 
// Target Devices: 
// Tool Versions: 
// Description: 
// 
// Dependencies: 
// 
// Revision:
// Revision 0.01 - File Created
// Additional Comments:
// 
//////////////////////////////////////////////////////////////////////////////////

// three bits input and two outputs. carry out will only be high if two inputs are high
module full_adder (
    input wire iA, iB, iCin,
    output wire oSum, oCout
);

// registors to hold 
    reg rSum, rCout;

    
// always block
always @ (iA or iB or iCin) begin // bitwise | in always time condition does not work, use or instead
    rSum = iA ^ iB ^ iCin; // rsum = (A xor B) xor Cin
    rCout = ((iA ^ iB) & iCin) | (iA & iB); // rcarry = (A&B) or ([A xor B] & Cin). do not use reg in condition or there will be time lag possibility
end

assign oSum = rSum;
assign oCout = rCout;
    
endmodule

ripple_carry_adder/ripple_carry_adder.srcs/sim_1/new/full_adder_TB.v
`timescale 1ns / 1ps
//////////////////////////////////////////////////////////////////////////////////
// Company: 
// Engineer: 
// 
// Create Date: 02/24/2023 07:11:31 AM
// Design Name: 
// Module Name: full_adder_TB
// Project Name: 
// Target Devices: 
// Tool Versions: 
// Description: 
// 
// Dependencies: 
// 
// Revision:
// Revision 0.01 - File Created
// Additional Comments:
// 
//////////////////////////////////////////////////////////////////////////////////


module full_adder_TB;
    
    // 1. declare testbench variables
    reg  riA, riB, rCin;
    wire wSum, wCout; 
    
    // 2. instantiate the deisgn and connect by position
    full_adder fa (riA, riB, rCin, wSum, wCout);
    
    // 3. provide stimulus to test the design
    initial begin
        // set stimulus to test the code
        riA <= 0;
        riB <= 0;
        rCin <= 0;
        #100 $finish;
    end
    // provide the toggling input in a style of truth table
    // this acts as the clock input
    always #40 riA = ~riA;
    always #20 riB = ~riB;
    always #10 rCin = ~rCin;
    
    // display output if there's a change in the input event
    // The format specifier %t:current simulation time. %d: value of the variable in decimal.
    always @(riA or riB or rCin) begin // cannot use bitwise | in always time condition
        $monitor("at time (in ns) = %t, A = %d B = %d Cin = %d Sum = %d Cout = %d", 
        $time, riA, riB, rCin, wSum, wCout);
    end
    
endmodule

ripple_carry_adder/ripple_carry_adder.sim/sim_1/behav/xsim/full_adder.vcd
$date
   Fri Feb 24 08:13:43 2023
$end
$version
  2020.1
$end
$timescale
  1ps
$end
$scope module full_adder_TB $end
$var reg 1 ! riA $end
$var reg 1 " riB $end
$var reg 1 # rCin $end
$var wire 1 $ wSum $end
$var wire 1 % wCout $end
$scope module fa $end
$var wire 1 & iA $end
$var wire 1 ' iB $end
$var wire 1 ( iCin $end
$var wire 1 $ oSum $end
$var wire 1 % oCout $end
$var reg 1 ) rSum $end
$var reg 1 * rCout $end
$upscope $end
$upscope $end
$enddefinitions $end
#0
$dumpvars
0!
0"
0#
0$
0%
0&
0'
0(
0)
0*
$end
#10000
1#
1$
1(
1)
#20000
1"
0#
1'
0(
#30000
1#
1(
#40000
1!
0"
0#
1&
0'
0(
#50000
1#
1(
#60000
1"
0#
1'
0(
#70000
1#
1(
#80000
0!
0"
0#
0$
0&
0'
0(
0)
#90000
1#
1$
1(
1)
